{
  "flow_name": "modules_released",
  "flow_subtype": "generated",
  "flow_type": "data_list",
  "rows": [
    {
      "id": "join",
      "status": "released",
      "number": "1",
      "facilitator": "male",
      "check_in_id": "check_in_1",
      "relax_id": "relax_4",
      "relax_id_list": [
        "relax_3",
        "relax_new",
        "relax_4"
      ],
      "play_id_list": [
        "happy_things",
        "gardening",
        "something_special"
      ],
      "book_id_list": [
        "little_shoots",
        "things_that_matter"
      ],
      "image_asset": "images/modules/join/join_title_image.svg",
      "attached_single_doc": "https://docs.google.com/document/d/1ULxQeRPqWjJyQp8dD_JBW3dUL-CCA47a5Fck-DtZH1E",
      "title": "JOIN",
      "_translations": {
        "title": {},
        "description_short": {},
        "description": {},
        "congratulation_text": {}
      },
      "_translatedFields": {
        "title": {
          "eng": "JOIN"
        },
        "description_short": {
          "eng": "Join ParentApp for Kids"
        },
        "description": {
          "eng": "Welcome to the ParentApp for Kids community!"
        },
        "congratulation_text": {
          "eng": "Well done for finishing the JOIN module!"
        }
      },
      "description_short": "Join ParentApp for Kids",
      "description": "Welcome to the ParentApp for Kids community!",
      "congratulation_text": "Well done for finishing the JOIN module!"
    },
    {
      "id": "connect",
      "status": "released",
      "number": "2",
      "facilitator": "female",
      "check_in_id": "check_in_10",
      "relax_id": "relax_10",
      "relax_id_list": [
        "relax_2",
        "relax_22",
        "relax_10"
      ],
      "play_id_list": [
        "what_makes_us_special",
        "pattern_play",
        "cooking_together"
      ],
      "book_id_list": [
        "to_the_top",
        "moms_red_coat"
      ],
      "image_asset": "images/modules/connect/connect_title_image.svg",
      "attached_single_doc": "https://docs.google.com/document/d/1ULxQeRPqWjJyQp8dD_JBW3dUL-CCA47a5Fck-DtZH1E",
      "title": "CONNECT",
      "_translations": {
        "title": {},
        "description_short": {},
        "description": {},
        "congratulation_text": {}
      },
      "_translatedFields": {
        "title": {
          "eng": "CONNECT"
        },
        "description_short": {
          "eng": "connecting with your child"
        },
        "description": {
          "eng": "Making time to connect with your child helps build a strong and positive relationship."
        },
        "congratulation_text": {
          "eng": "Well done for finishing the CONNECT module!"
        }
      },
      "description_short": "connecting with your child",
      "description": "Making time to connect with your child helps build a strong and positive relationship.",
      "congratulation_text": "Well done for finishing the CONNECT module!"
    },
    {
      "id": "create",
      "status": "released",
      "number": "3",
      "facilitator": "male",
      "check_in_id": "check_in_8",
      "relax_id": "relax_14",
      "relax_id_list": [
        "relax_21",
        "relax_5",
        "relax_14"
      ],
      "play_id_list": [
        "household_helpers",
        "music_and_dancing",
        "walking_together"
      ],
      "book_id_list": [
        "babys_first_photo",
        "shongololo_s_shoes"
      ],
      "image_asset": "images/modules/create/create_title_image.svg",
      "attached_single_doc": "https://docs.google.com/document/d/1ULxQeRPqWjJyQp8dD_JBW3dUL-CCA47a5Fck-DtZH1E",
      "title": "CREATE",
      "_translations": {
        "title": {},
        "description_short": {},
        "description": {},
        "congratulation_text": {}
      },
      "_translatedFields": {
        "title": {
          "eng": "CREATE"
        },
        "description_short": {
          "eng": "creating a positive environment"
        },
        "description": {
          "eng": "Create a positive and supportive environment for your child to learn in."
        },
        "congratulation_text": {
          "eng": "Well done for finishing the CREATE module!"
        }
      },
      "description_short": "creating a positive environment",
      "description": "Create a positive and supportive environment for your child to learn in.",
      "congratulation_text": "Well done for finishing the CREATE module!"
    },
    {
      "id": "play",
      "status": "released",
      "number": "4",
      "facilitator": "female",
      "check_in_id": "check_in_13",
      "relax_id": "relax_20",
      "relax_id_list": [
        "relax_8",
        "relax_13",
        "relax_20"
      ],
      "play_id_list": [
        "favourite_play",
        "act_the_story",
        "shadow_movie"
      ],
      "book_id_list": [
        "lesedis_sandbox",
        "lefas_bath"
      ],
      "image_asset": "images/modules/play/play_title_image.svg",
      "attached_single_doc": "https://docs.google.com/document/d/1ULxQeRPqWjJyQp8dD_JBW3dUL-CCA47a5Fck-DtZH1E",
      "title": "PLAY",
      "_translations": {
        "title": {},
        "description_short": {},
        "description": {},
        "congratulation_text": {}
      },
      "_translatedFields": {
        "title": {
          "eng": "PLAY"
        },
        "description_short": {
          "eng": "playful interactions"
        },
        "description": {
          "eng": "Play is the best way for children to learn. Let’s look at ways to support your child through play."
        },
        "congratulation_text": {
          "eng": "Well done for finishing the PLAY module!"
        }
      },
      "description_short": "playful interactions",
      "description": "Play is the best way for children to learn. Let’s look at ways to support your child through play.",
      "congratulation_text": "Well done for finishing the PLAY module!"
    }
  ]
}